pyrecommend/rec.py
pyrecommend/__init__.py
pyrecommend/similarity.py
pyrecommend/vec_util.py
pyrecommend/helpers.py
pyrecommend-0.1.dev5.dist-info/metadata.json
pyrecommend-0.1.dev5.dist-info/WHEEL
pyrecommend-0.1.dev5.dist-info/RECORD
pyrecommend-0.1.dev5.dist-info/METADATA
pyrecommend-0.1.dev5.dist-info/top_level.txt
pyrecommend-0.1.dev5.dist-info/DESCRIPTION.rst
