Metadata-Version: 2.0
Name: pyrecommend
Version: 0.1.dev5
Summary: A simple collaborative filtering algorithm for Python.
Home-page: https://github.com/dan-passaro/pyrecommend/
Author: Dan Passaro
Author-email: danpassaro@gmail.com
License: MIT
Platform: UNKNOWN
